README.md
setup.py
vertices/__init__.py
vertices.egg-info/PKG-INFO
vertices.egg-info/SOURCES.txt
vertices.egg-info/dependency_links.txt
vertices.egg-info/requires.txt
vertices.egg-info/top_level.txt